blog/__init__.py
blog/admin.py
blog/apps.py
blog/feed.py
blog/models.py
blog/tests.py
blog/urls.py
blog/views.py
blog/migrations/__init__.py
cheap_local_websites_blog-0.0.2.dist-info/LICENSE
cheap_local_websites_blog-0.0.2.dist-info/METADATA
cheap_local_websites_blog-0.0.2.dist-info/WHEEL
cheap_local_websites_blog-0.0.2.dist-info/top_level.txt
cheap_local_websites_blog-0.0.2.dist-info/RECORD
