Metadata-Version: 2.1
Name: cheap-local-websites-blog
Version: 0.0.2
Summary: A dynamic blog application including rss feed
Home-page: https://www.cheaplocalwebsites.com
Author: John
Author-email: john@cheaplocalwebsites.com
License: UNKNOWN
Platform: UNKNOWN
Classifier: Programming Language :: Python :: 3
Classifier: License :: OSI Approved :: MIT License
Classifier: Operating System :: OS Independent
Requires-Python: >=3.6
